rara_digitizer/__init__.py
rara_digitizer/exceptions.py
rara_digitizer/converters/__init__.py
rara_digitizer/converters/doc2docx.py
rara_digitizer/converters/img2pdf.py
rara_digitizer/converters/pdf2img.py
rara_digitizer/factory/__init__.py
rara_digitizer/factory/file_handler_factory.py
rara_digitizer/factory/resource_manager.py
rara_digitizer/factory/resources/__init__.py
rara_digitizer/factory/resources/base.py
rara_digitizer/factory/resources/image_classificator.py
rara_digitizer/factory/resources/quality_evaluator.py
rara_digitizer/factory/resources/tesseract.py
rara_digitizer/factory/resources/yolo.py
rara_digitizer/handlers/__init__.py
rara_digitizer/handlers/base_handler.py
rara_digitizer/handlers/docx_handler.py
rara_digitizer/handlers/epub_handler.py
rara_digitizer/handlers/html_handler.py
rara_digitizer/handlers/metsalto_handler.py
rara_digitizer/handlers/pdf_handler.py
rara_digitizer/handlers/txt_handler.py
rara_digitizer/illustration_detector/__init__.py
rara_digitizer/illustration_detector/yolo.py
rara_digitizer/ocr/__init__.py
rara_digitizer/ocr/processors/__init__.py
rara_digitizer/ocr/processors/ocr_processor.py
rara_digitizer/tools/__init__.py
rara_digitizer/tools/image_classification.py
rara_digitizer/tools/ocr_strategy.py
rara_digitizer/tools/text_postproc.py
rara_digitizer/utils/__init__.py
rara_digitizer/utils/constants.py
rara_digitizer/utils/download.py
rara_digitizer/utils/load_class.py
rara_digitizer-1.5.1.dist-info/licenses/LICENSE
rara_digitizer-1.5.1.dist-info/METADATA
rara_digitizer-1.5.1.dist-info/WHEEL
rara_digitizer-1.5.1.dist-info/top_level.txt
rara_digitizer-1.5.1.dist-info/RECORD
