Metadata-Version: 2.4
Name: rara-digitizer
Version: 1.5.1
Summary: Document reader with OCR & image detection support.
License:        GNU GENERAL PUBLIC LICENSE
Classifier: Programming Language :: Python :: 3
Classifier: Programming Language :: Python :: 3.10
Classifier: Programming Language :: Python :: 3.11
Classifier: Programming Language :: Python :: 3.12
Classifier: Intended Audience :: Science/Research
Requires-Python: >=3.10
License-File: LICENSE
Requires-Dist: editdistance==0.8.1
Requires-Dist: matplotlib==3.9.2
Requires-Dist: numpy==1.26.4
Requires-Dist: ocrmypdf==16.4.3
Requires-Dist: opencv_python==4.10.0.84
Requires-Dist: pdf2image==1.17.0
Requires-Dist: pdfplumber==0.11.3
Requires-Dist: Pillow==10.4.0
Requires-Dist: PyPDF2==3.0.1
Requires-Dist: pytesseract==0.3.10
Requires-Dist: python_magic==0.4.27
Requires-Dist: ultralytics==8.3.2
Requires-Dist: universal_pathlib==0.2.2
Requires-Dist: python-docx==1.1.2
Requires-Dist: img2pdf==0.6.1
Requires-Dist: ebooklib==0.18
Requires-Dist: pypdf==5.0.0
Requires-Dist: beautifulsoup4==4.12.3
Requires-Dist: langdetect==1.0.9
Requires-Dist: environs==11.2.1
Requires-Dist: rara-text-evaluator==1.0.0
Requires-Dist: transformers==4.47.0
Requires-Dist: rara-tools==0.9.*
Requires-Dist: django-environ==0.12.0
Provides-Extra: testing
Requires-Dist: pytest>=8.0; extra == "testing"
Provides-Extra: cpu
Requires-Dist: torch==2.3.1+cpu; extra == "cpu"
Requires-Dist: torchvision==0.20.1+cpu; extra == "cpu"
Dynamic: license-file
